<?xml version="1.0" encoding="UTF-8" ?>
<scene>
  <material>
    <name>Bark</name>
    <data>
      <type>Lambertian</type>
      <diffuse>
        <color>209 147 124 255</color>
      </diffuse>
    </data>
  </material>
  
  <material>
    <name>Leaves</name>
    <data>
      <type>Lambertian</type>
      <diffuse>
        <color>10 230 100 255</color>
      </diffuse>
    </data>
  </material>
  
      <cubemap>
        <name>EnvMap</name>
        <data>
            <file>data/textures/Envir/NissiBeach/</file>
        </data>
    </cubemap>


	
    <mesh>
        <name>SkyBox.obj</name>
        <data>
            <file>data/meshes/skybox.obj</file>
        </data>
    </mesh>	
    
	<object>
		<name>Floor1</name>
		<data>
			<mesh>Floor1.obj</mesh>
			<material>Bark</material>
		</data>
	</object>	
	
	    <material>
        <name>EnvironmentLight</name>
        <data>
            <type>Environment</type>
        </data>
    </material>
    

  	<mesh>
		<name>Floor1.obj</name>
		<data>
			<file>data/meshes/Floor1.obj</file>
			
		</data>
	</mesh>



    	
    <object>
        <name>Camera</name>
        <data type="SceneCamera">
            <zPlanes>0.02 1000.0</zPlanes>
            <perspective>0.01 0.01</perspective>
            <exposure>1</exposure>
            <rotation>0 90 0</rotation>
            <translation>5 1 9</translation>
        </data>
    </object>
</scene>
